<?xml version="1.0" encoding="UTF-8"?>
<tour appversion="7.1.4" start="node10" hassounds="1" apprev="20938">
  <panorama id="node10">
    <input levelbias="0.400" levelbiashidpi="1.000" levelingroll="0" height="3657" leveltileurl="tiles/node10/cf_%c/l_%l/c_%x/tile_%y.jpg" leveltilesize="510" width="3657" levelingpitch="0" overlap="1">
      <level height="3657" preload="0" width="3657" predecode="0"/>
      <level height="1828" preload="0" width="1828" predecode="0"/>
      <level height="914" preload="0" width="914" predecode="0"/>
      <level height="457" preload="1" width="457" predecode="1"/>
      <preview color="0x808080" strip="1"/>
    </input>
    <view pannorth="80.7658" fovmode="2">
      <start tilt="0" projection="4" pan="0" fov="100"/>
      <flyin tilt="-90" projection="9" pan="0" fov="170"/>
      <min fovpixel="2" tilt="-90" pan="0"/>
      <max fovstereographic="330" tilt="90" fovfisheye="360" scaletofit="1" pan="360" fov="90"/>
    </view>
    <userdata longitude="121.61282085" heading="80.7658" tags="PTGuioutput" title="站點 A 入口" info="" author="James Lee" latitude="23.98066144" comment="" description="" nodeid="node10" copyright="jp-image.space" datetime="2024/10/14 11:18" customnodeid="" source="">
      <mapcoords y_floorplan_percent="36.3943" x="0.531464" x_floorplan_percent="29.3961" y="-0.593262" mapid="FloorPlan01"/>
    </userdata>
    <hotspots height="20" smoothmovement="0" width="180" wordwrap="1">
      <label enabled="1" textcolor="0x000000" borderradius="1" wordwrap="1" bordercolor="0x000000" height="20" backgroundcolor="0xffffff" backgroundalpha="1" border="1" borderalpha="1" textalpha="1" width="180" background="1"/>
      <polystyle backgroundalpha="0.25098" backgroundcolor="0x0000ff" borderalpha="1" handcursor="1" bordercolor="0x0000ff" mode="0"/>
      <hotspot skinid="ht_node" title="站點 Ｂ園區導覽地圖" id="Point01" target="$fwd" tilt="0" distance="11.205" description="" url="{node11}" pan="-28.222"/>
    </hotspots>
    <media/>
    <transition softedge="0" enabled="1" zoomafteroutfov="40" zoomspeed="2" delay="none" zoomoutpause="1" blendcolor="0x000000" blendtime="1" zoomafterinfov="140" zoomin="0" zoomout="0" type="crossdissolve" zoomfov="40"/>
    <animation clipsrandom="0" useinautorotation="0" syncanimationwithvideo="0" animsequence="Animation01"/>
    <control invertwheel="0" contextvr="1" speedwheel="1" dblclickfullscreen="0" contextprojections="0" lockedwheel="0" rubberband="0" zoomcentercursor="1" contextfullscreen="1" sensitivity="8" simulatemass="1" invertcontrol="1" lockedmouse="0" hideabout="0" lockedkeyboard="0" lockedkeyboardzoom="0"/>
  </panorama>
  <panorama id="node11">
    <input levelbias="0.400" levelbiashidpi="1.000" levelingroll="0" height="3658" leveltileurl="tiles/node11/cf_%c/l_%l/c_%x/tile_%y.jpg" leveltilesize="510" width="3658" levelingpitch="0" overlap="1">
      <level height="3658" preload="0" width="3658" predecode="0"/>
      <level height="1829" preload="0" width="1829" predecode="0"/>
      <level height="914" preload="0" width="914" predecode="0"/>
      <level height="457" preload="1" width="457" predecode="1"/>
      <preview color="0x808080" strip="1"/>
    </input>
    <view pannorth="-15.2426" fovmode="2">
      <start tilt="0" projection="4" pan="90" fov="100"/>
      <flyin tilt="-90" projection="9" pan="0" fov="170"/>
      <min fovpixel="2" tilt="-90" pan="0"/>
      <max fovstereographic="330" tilt="90" fovfisheye="360" scaletofit="1" pan="360" fov="90"/>
    </view>
    <userdata longitude="121.61293054" heading="-15.2426" tags="PTGuioutput" title="站點 Ｂ園區導覽地圖" info="" author="James Lee" latitude="23.98067193" comment="" description="" nodeid="node11" copyright="jp-image.space" datetime="2024/10/14 12:02" customnodeid="" source="">
      <mapcoords y_floorplan_percent="36.5206" x="0.650253" x_floorplan_percent="35.9666" y="-0.595322" mapid="FloorPlan01"/>
    </userdata>
    <hotspots height="20" smoothmovement="0" width="180" wordwrap="1">
      <label enabled="1" textcolor="0x000000" borderradius="1" wordwrap="1" bordercolor="0x000000" height="20" backgroundcolor="0xffffff" backgroundalpha="1" border="1" borderalpha="1" textalpha="1" width="180" background="1"/>
      <polystyle backgroundalpha="0.25098" backgroundcolor="0x0000ff" borderalpha="1" handcursor="1" bordercolor="0x0000ff" mode="0"/>
      <hotspot skinid="ht_node" title="站點 C OOA 烘焙" id="Point02" target="$fwd" tilt="0.68" distance="19.9666" description="" url="{node12}" pan="-110.3"/>
      <hotspot skinid="ht_node" title="站點 E Doga | 定置漁場" id="Point03" target="$fwd" tilt="4.34" distance="10.9069" description="" url="{node14}" pan="-230.69"/>
      <hotspot skinid="ht_node" title="站點 J" id="Point04" target="$fwd" tilt="1.17" distance="39.1671" description="" url="{node19}" pan="-187.2"/>
      <hotspot skinid="ht_node" title="站點 A 入口" id="Point01" target="$fwd" tilt="0" distance="11.205" description="" url="{node10}" pan="55.7696"/>
    </hotspots>
    <media/>
    <transition softedge="0" enabled="1" zoomafteroutfov="40" zoomspeed="2" delay="none" zoomoutpause="1" blendcolor="0x000000" blendtime="1" zoomafterinfov="140" zoomin="0" zoomout="0" type="crossdissolve" zoomfov="40"/>
    <animation clipsrandom="0" useinautorotation="0" syncanimationwithvideo="0" animsequence="Animation01"/>
    <control invertwheel="0" contextvr="1" speedwheel="1" dblclickfullscreen="0" contextprojections="0" lockedwheel="0" rubberband="0" zoomcentercursor="1" contextfullscreen="1" sensitivity="8" simulatemass="1" invertcontrol="1" lockedmouse="0" hideabout="0" lockedkeyboard="0" lockedkeyboardzoom="0"/>
  </panorama>
  <panorama id="node12">
    <input levelbias="0.400" levelbiashidpi="1.000" levelingroll="0" height="3660" leveltileurl="tiles/node12/cf_%c/l_%l/c_%x/tile_%y.jpg" leveltilesize="510" width="3660" levelingpitch="0" overlap="1">
      <level height="3660" preload="0" width="3660" predecode="0"/>
      <level height="1830" preload="0" width="1830" predecode="0"/>
      <level height="915" preload="0" width="915" predecode="0"/>
      <level height="457" preload="1" width="457" predecode="1"/>
      <preview color="0x808080" strip="1"/>
    </input>
    <view pannorth="6.87211" fovmode="2">
      <start tilt="0" projection="4" pan="90" fov="100"/>
      <flyin tilt="-90" projection="9" pan="0" fov="170"/>
      <min fovpixel="2" tilt="-90" pan="0"/>
      <max fovstereographic="330" tilt="90" fovfisheye="360" scaletofit="1" pan="360" fov="90"/>
    </view>
    <userdata longitude="121.61312579" heading="6.87211" tags="PTGuioutput" title="站點 C OOA 烘焙" info="" author="James Lee" latitude="23.98065149" comment="" description="" nodeid="node12" copyright="jp-image.space" datetime="2024/10/14 10:46" customnodeid="" source="">
      <mapcoords y_floorplan_percent="34.1196" x="0.847321" x_floorplan_percent="46.8667" y="-0.556183" mapid="FloorPlan01"/>
    </userdata>
    <hotspots height="20" smoothmovement="0" width="180" wordwrap="1">
      <label enabled="1" textcolor="0x000000" borderradius="1" wordwrap="1" bordercolor="0x000000" height="20" backgroundcolor="0xffffff" backgroundalpha="1" border="1" borderalpha="1" textalpha="1" width="180" background="1"/>
      <polystyle backgroundalpha="0.25098" backgroundcolor="0x0000ff" borderalpha="1" handcursor="1" bordercolor="0x0000ff" mode="0"/>
      <hotspot skinid="ht_node" title="站點 D 牆面介紹" id="Point01" target="$fwd" tilt="2.08" distance="17.3572" description="" url="{node13}" pan="-115.35"/>
      <hotspot skinid="ht_node" title="站點 F 台灣地方創生基金會" id="Point02" target="$fwd" tilt="-0.36" distance="15.022" description="" url="{node15}" pan="-166.06"/>
      <hotspot skinid="ht_node" title="站點 Ｂ園區導覽地圖" id="Point03" target="$fwd" tilt="0" distance="19.9666" description="" url="{node11}" pan="90.3358"/>
    </hotspots>
    <media/>
    <transition softedge="0" enabled="1" zoomafteroutfov="40" zoomspeed="2" delay="none" zoomoutpause="1" blendcolor="0x000000" blendtime="1" zoomafterinfov="140" zoomin="0" zoomout="0" type="crossdissolve" zoomfov="40"/>
    <animation clipsrandom="0" useinautorotation="0" syncanimationwithvideo="0" animsequence="Animation01"/>
    <control invertwheel="0" contextvr="1" speedwheel="1" dblclickfullscreen="0" contextprojections="0" lockedwheel="0" rubberband="0" zoomcentercursor="1" contextfullscreen="1" sensitivity="8" simulatemass="1" invertcontrol="1" lockedmouse="0" hideabout="0" lockedkeyboard="0" lockedkeyboardzoom="0"/>
  </panorama>
  <panorama id="node13">
    <input levelbias="0.400" levelbiashidpi="1.000" levelingroll="0" height="3656" leveltileurl="tiles/node13/cf_%c/l_%l/c_%x/tile_%y.jpg" leveltilesize="510" width="3656" levelingpitch="0" overlap="1">
      <level height="3656" preload="0" width="3656" predecode="0"/>
      <level height="1828" preload="0" width="1828" predecode="0"/>
      <level height="914" preload="0" width="914" predecode="0"/>
      <level height="457" preload="1" width="457" predecode="1"/>
      <preview color="0x808080" strip="1"/>
    </input>
    <view pannorth="41.5523" fovmode="2">
      <start tilt="0" projection="4" pan="90" fov="100"/>
      <flyin tilt="-90" projection="9" pan="0" fov="170"/>
      <min fovpixel="2" tilt="-90" pan="0"/>
      <max fovstereographic="330" tilt="90" fovfisheye="360" scaletofit="1" pan="360" fov="90"/>
    </view>
    <userdata longitude="121.61327044" heading="41.5523" tags="PTGuioutput" title="站點 D 牆面介紹" info="" author="James Lee" latitude="23.98056843" comment="" description="" nodeid="node13" copyright="jp-image.space" datetime="2024/10/14 10:54" customnodeid="" source="">
      <mapcoords y_floorplan_percent="36.7313" x="1.01624" x_floorplan_percent="56.2096" y="-0.598755" mapid="FloorPlan01"/>
    </userdata>
    <hotspots height="20" smoothmovement="0" width="180" wordwrap="1">
      <label enabled="1" textcolor="0x000000" borderradius="1" wordwrap="1" bordercolor="0x000000" height="20" backgroundcolor="0xffffff" backgroundalpha="1" border="1" borderalpha="1" textalpha="1" width="180" background="1"/>
      <polystyle backgroundalpha="0.25098" backgroundcolor="0x0000ff" borderalpha="1" handcursor="1" bordercolor="0x0000ff" mode="0"/>
      <hotspot skinid="ht_node" title="站點 C OOA 烘焙" id="Point02" target="$fwd" tilt="2.83" distance="17.3572" description="" url="{node12}" pan="-260.77"/>
      <hotspot skinid="ht_node" title="站點 L" id="Point01" target="$fwd" tilt="1.65" distance="35.391" description="" url="{node21}" pan="-149.67"/>
    </hotspots>
    <media/>
    <transition softedge="0" enabled="1" zoomafteroutfov="40" zoomspeed="2" delay="none" zoomoutpause="1" blendcolor="0x000000" blendtime="1" zoomafterinfov="140" zoomin="0" zoomout="0" type="crossdissolve" zoomfov="40"/>
    <animation clipsrandom="0" useinautorotation="0" syncanimationwithvideo="0" animsequence="Animation01"/>
    <control invertwheel="0" contextvr="1" speedwheel="1" dblclickfullscreen="0" contextprojections="0" lockedwheel="0" rubberband="0" zoomcentercursor="1" contextfullscreen="1" sensitivity="8" simulatemass="1" invertcontrol="1" lockedmouse="0" hideabout="0" lockedkeyboard="0" lockedkeyboardzoom="0"/>
  </panorama>
  <panorama id="node14">
    <input levelbias="0.400" levelbiashidpi="1.000" levelingroll="0" height="3658" leveltileurl="tiles/node14/cf_%c/l_%l/c_%x/tile_%y.jpg" leveltilesize="510" width="3658" levelingpitch="0" overlap="1">
      <level height="3658" preload="0" width="3658" predecode="0"/>
      <level height="1829" preload="0" width="1829" predecode="0"/>
      <level height="914" preload="0" width="914" predecode="0"/>
      <level height="457" preload="1" width="457" predecode="1"/>
      <preview color="0x808080" strip="1"/>
    </input>
    <view pannorth="-70.4509" fovmode="2">
      <start tilt="0" projection="4" pan="90" fov="100"/>
      <flyin tilt="-90" projection="9" pan="0" fov="170"/>
      <min fovpixel="2" tilt="-90" pan="0"/>
      <max fovstereographic="330" tilt="90" fovfisheye="360" scaletofit="1" pan="360" fov="90"/>
    </view>
    <userdata longitude="121.61286816" heading="-70.4509" tags="PTGuioutput" title="站點 E Doga | 定置漁場" info="" author="James Lee" latitude="23.98059210" comment="" description="" nodeid="node14" copyright="jp-image.space" datetime="2024/10/14 10:41" customnodeid="" source="">
      <mapcoords y_floorplan_percent="42.9655" x="0.617981" x_floorplan_percent="34.1815" y="-0.700378" mapid="FloorPlan01"/>
    </userdata>
    <hotspots height="20" smoothmovement="0" width="180" wordwrap="1">
      <label enabled="1" textcolor="0x000000" borderradius="1" wordwrap="1" bordercolor="0x000000" height="20" backgroundcolor="0xffffff" backgroundalpha="1" border="1" borderalpha="1" textalpha="1" width="180" background="1"/>
      <polystyle backgroundalpha="0.25098" backgroundcolor="0x0000ff" borderalpha="1" handcursor="1" bordercolor="0x0000ff" mode="0"/>
      <hotspot skinid="ht_node" title="站點 Ｂ園區導覽地圖" id="Point01" target="$fwd" tilt="0.98" distance="10.9069" description="" url="{node11}" pan="-104.76"/>
    </hotspots>
    <media/>
    <transition softedge="0" enabled="1" zoomafteroutfov="40" zoomspeed="2" delay="none" zoomoutpause="1" blendcolor="0x000000" blendtime="1" zoomafterinfov="140" zoomin="0" zoomout="0" type="crossdissolve" zoomfov="40"/>
    <animation clipsrandom="0" useinautorotation="0" syncanimationwithvideo="0" animsequence="Animation01"/>
    <control invertwheel="0" contextvr="1" speedwheel="1" dblclickfullscreen="0" contextprojections="0" lockedwheel="0" rubberband="0" zoomcentercursor="1" contextfullscreen="1" sensitivity="8" simulatemass="1" invertcontrol="1" lockedmouse="0" hideabout="0" lockedkeyboard="0" lockedkeyboardzoom="0"/>
  </panorama>
  <panorama id="node15">
    <input levelbias="0.400" levelbiashidpi="1.000" levelingroll="0" height="3661" leveltileurl="tiles/node15/cf_%c/l_%l/c_%x/tile_%y.jpg" leveltilesize="510" width="3661" levelingpitch="0" overlap="1">
      <level height="3661" preload="0" width="3661" predecode="0"/>
      <level height="1830" preload="0" width="1830" predecode="0"/>
      <level height="915" preload="0" width="915" predecode="0"/>
      <level height="457" preload="1" width="457" predecode="1"/>
      <preview color="0x808080" strip="1"/>
    </input>
    <view pannorth="157.237" fovmode="2">
      <start tilt="0" projection="4" pan="90" fov="100"/>
      <flyin tilt="-90" projection="9" pan="0" fov="170"/>
      <min fovpixel="2" tilt="-90" pan="0"/>
      <max fovstereographic="330" tilt="90" fovfisheye="360" scaletofit="1" pan="360" fov="90"/>
    </view>
    <userdata longitude="121.61313883" heading="157.237" tags="PTGuioutput" title="站點 F 台灣地方創生基金會" info="" author="James Lee" latitude="23.98051692" comment="" description="" nodeid="node15" copyright="jp-image.space" datetime="2024/10/14 10:50" customnodeid="" source="">
      <mapcoords y_floorplan_percent="42.6285" x="0.906372" x_floorplan_percent="50.1329" y="-0.694885" mapid="FloorPlan01"/>
    </userdata>
    <hotspots height="20" smoothmovement="0" width="180" wordwrap="1">
      <label enabled="1" textcolor="0x000000" borderradius="1" wordwrap="1" bordercolor="0x000000" height="20" backgroundcolor="0xffffff" backgroundalpha="1" border="1" borderalpha="1" textalpha="1" width="180" background="1"/>
      <polystyle backgroundalpha="0.25098" backgroundcolor="0x0000ff" borderalpha="1" handcursor="1" bordercolor="0x0000ff" mode="0"/>
      <hotspot skinid="ht_node" title="站點 C OOA 烘焙" id="Point01" target="$fwd" tilt="0.07" distance="15.022" description="" url="{node12}" pan="-199.56"/>
    </hotspots>
    <media/>
    <transition softedge="0" enabled="1" zoomafteroutfov="40" zoomspeed="2" delay="none" zoomoutpause="1" blendcolor="0x000000" blendtime="1" zoomafterinfov="140" zoomin="0" zoomout="0" type="crossdissolve" zoomfov="40"/>
    <animation clipsrandom="0" useinautorotation="0" syncanimationwithvideo="0" animsequence="Animation01"/>
    <control invertwheel="0" contextvr="1" speedwheel="1" dblclickfullscreen="0" contextprojections="0" lockedwheel="0" rubberband="0" zoomcentercursor="1" contextfullscreen="1" sensitivity="8" simulatemass="1" invertcontrol="1" lockedmouse="0" hideabout="0" lockedkeyboard="0" lockedkeyboardzoom="0"/>
  </panorama>
  <panorama id="node16">
    <input levelbias="0.400" levelbiashidpi="1.000" levelingroll="0" height="3660" leveltileurl="tiles/node16/cf_%c/l_%l/c_%x/tile_%y.jpg" leveltilesize="510" width="3660" levelingpitch="0" overlap="1">
      <level height="3660" preload="0" width="3660" predecode="0"/>
      <level height="1830" preload="0" width="1830" predecode="0"/>
      <level height="915" preload="0" width="915" predecode="0"/>
      <level height="457" preload="1" width="457" predecode="1"/>
      <preview color="0x808080" strip="1"/>
    </input>
    <view pannorth="-124.209" fovmode="2">
      <start tilt="0" projection="4" pan="90" fov="100"/>
      <flyin tilt="-90" projection="9" pan="0" fov="170"/>
      <min fovpixel="2" tilt="-90" pan="0"/>
      <max fovstereographic="330" tilt="90" fovfisheye="360" scaletofit="1" pan="360" fov="90"/>
    </view>
    <userdata longitude="121.61266559" heading="-124.209" tags="PTGuioutput" title="站點 G 家咖哩" info="" author="James Lee" latitude="23.98041674" comment="" description="" nodeid="node16" copyright="jp-image.space" datetime="2024/10/14 10:34" customnodeid="" source="">
      <mapcoords y_floorplan_percent="58.2982" x="0.481339" x_floorplan_percent="26.6236" y="-0.950317" mapid="FloorPlan01"/>
    </userdata>
    <hotspots height="20" smoothmovement="0" width="180" wordwrap="1">
      <label enabled="1" textcolor="0x000000" borderradius="1" wordwrap="1" bordercolor="0x000000" height="20" backgroundcolor="0xffffff" backgroundalpha="1" border="1" borderalpha="1" textalpha="1" width="180" background="1"/>
      <polystyle backgroundalpha="0.25098" backgroundcolor="0x0000ff" borderalpha="1" handcursor="1" bordercolor="0x0000ff" mode="0"/>
      <hotspot skinid="ht_node" title="站點Ｑ 防空洞" id="Point01" target="$fwd" tilt="0" distance="7.14238" description="" url="{node1}" pan="-88.6429"/>
      <hotspot skinid="ht_node" title="站點 H 炸彈檸檬茶" id="Point02" target="$fwd" tilt="0" distance="10.5386" description="" url="{node17}" pan="-232.95"/>
    </hotspots>
    <media/>
    <transition softedge="0" enabled="1" zoomafteroutfov="40" zoomspeed="2" delay="none" zoomoutpause="1" blendcolor="0x000000" blendtime="1" zoomafterinfov="140" zoomin="0" zoomout="0" type="crossdissolve" zoomfov="40"/>
    <animation clipsrandom="0" useinautorotation="0" syncanimationwithvideo="0" animsequence="Animation01"/>
    <control invertwheel="0" contextvr="1" speedwheel="1" dblclickfullscreen="0" contextprojections="0" lockedwheel="0" rubberband="0" zoomcentercursor="1" contextfullscreen="1" sensitivity="8" simulatemass="1" invertcontrol="1" lockedmouse="0" hideabout="0" lockedkeyboard="0" lockedkeyboardzoom="0"/>
  </panorama>
  <panorama id="node17">
    <input levelbias="0.400" levelbiashidpi="1.000" levelingroll="0" height="3663" leveltileurl="tiles/node17/cf_%c/l_%l/c_%x/tile_%y.jpg" leveltilesize="510" width="3663" levelingpitch="0" overlap="1">
      <level height="3663" preload="0" width="3663" predecode="0"/>
      <level height="1831" preload="0" width="1831" predecode="0"/>
      <level height="915" preload="0" width="915" predecode="0"/>
      <level height="457" preload="1" width="457" predecode="1"/>
      <preview color="0x808080" strip="1"/>
    </input>
    <view pannorth="-156.751" fovmode="2">
      <start tilt="0" projection="4" pan="90" fov="100"/>
      <flyin tilt="-90" projection="9" pan="0" fov="170"/>
      <min fovpixel="2" tilt="-90" pan="0"/>
      <max fovstereographic="330" tilt="90" fovfisheye="360" scaletofit="1" pan="360" fov="90"/>
    </view>
    <userdata longitude="121.61276382" heading="-156.751" tags="PTGuioutput" title="站點 H 炸彈檸檬茶" info="" author="James Lee" latitude="23.98038629" comment="" description="" nodeid="node17" copyright="jp-image.space" datetime="2024/10/14 10:30" customnodeid="" source="">
      <mapcoords y_floorplan_percent="58.3404" x="0.587769" x_floorplan_percent="32.5104" y="-0.951004" mapid="FloorPlan01"/>
    </userdata>
    <hotspots height="20" smoothmovement="0" width="180" wordwrap="1">
      <label enabled="1" textcolor="0x000000" borderradius="1" wordwrap="1" bordercolor="0x000000" height="20" backgroundcolor="0xffffff" backgroundalpha="1" border="1" borderalpha="1" textalpha="1" width="180" background="1"/>
      <polystyle backgroundalpha="0.25098" backgroundcolor="0x0000ff" borderalpha="1" handcursor="1" bordercolor="0x0000ff" mode="0"/>
      <hotspot skinid="ht_node" title="站點 G 家咖哩" id="Point01" target="$fwd" tilt="-0.63" distance="10.5386" description="" url="{node16}" pan="-84.6007"/>
      <hotspot skinid="ht_node" title="站點 I 貓丁目冰淇淋" id="Point02" target="$fwd" tilt="0" distance="11.7711" description="" url="{node18}" pan="-263.423"/>
      <hotspot skinid="ht_node" title="站點 Ｏ" id="Point03" target="$fwd" tilt="-0.84" distance="24.6325" description="" url="{node24}" pan="-354.69"/>
    </hotspots>
    <media/>
    <transition softedge="0" enabled="1" zoomafteroutfov="40" zoomspeed="2" delay="none" zoomoutpause="1" blendcolor="0x000000" blendtime="1" zoomafterinfov="140" zoomin="0" zoomout="0" type="crossdissolve" zoomfov="40"/>
    <animation clipsrandom="0" useinautorotation="0" syncanimationwithvideo="0" animsequence="Animation01"/>
    <control invertwheel="0" contextvr="1" speedwheel="1" dblclickfullscreen="0" contextprojections="0" lockedwheel="0" rubberband="0" zoomcentercursor="1" contextfullscreen="1" sensitivity="8" simulatemass="1" invertcontrol="1" lockedmouse="0" hideabout="0" lockedkeyboard="0" lockedkeyboardzoom="0"/>
  </panorama>
  <panorama id="node18">
    <input levelbias="0.400" levelbiashidpi="1.000" levelingroll="0" height="3660" leveltileurl="tiles/node18/cf_%c/l_%l/c_%x/tile_%y.jpg" leveltilesize="510" width="3660" levelingpitch="0" overlap="1">
      <level height="3660" preload="0" width="3660" predecode="0"/>
      <level height="1830" preload="0" width="1830" predecode="0"/>
      <level height="915" preload="0" width="915" predecode="0"/>
      <level height="457" preload="1" width="457" predecode="1"/>
      <preview color="0x808080" strip="1"/>
    </input>
    <view pannorth="-157.924" fovmode="2">
      <start tilt="0" projection="4" pan="90" fov="100"/>
      <flyin tilt="-90" projection="9" pan="0" fov="170"/>
      <min fovpixel="2" tilt="-90" pan="0"/>
      <max fovstereographic="330" tilt="90" fovfisheye="360" scaletofit="1" pan="360" fov="90"/>
    </view>
    <userdata longitude="121.61287481" heading="-157.924" tags="PTGuioutput" title="站點 I 貓丁目冰淇淋" info="" author="James Lee" latitude="23.98035592" comment="" description="" nodeid="node18" copyright="jp-image.space" datetime="2024/10/14 10:23" customnodeid="" source="">
      <mapcoords y_floorplan_percent="58.214" x="0.705872" x_floorplan_percent="39.0429" y="-0.948944" mapid="FloorPlan01"/>
    </userdata>
    <hotspots height="20" smoothmovement="0" width="180" wordwrap="1">
      <label enabled="1" textcolor="0x000000" borderradius="1" wordwrap="1" bordercolor="0x000000" height="20" backgroundcolor="0xffffff" backgroundalpha="1" border="1" borderalpha="1" textalpha="1" width="180" background="1"/>
      <polystyle backgroundalpha="0.25098" backgroundcolor="0x0000ff" borderalpha="1" handcursor="1" bordercolor="0x0000ff" mode="0"/>
      <hotspot skinid="ht_node" title="站點 H 炸彈檸檬茶" id="Point01" target="$fwd" tilt="0" distance="11.7711" description="" url="{node17}" pan="-84.5958"/>
      <hotspot skinid="ht_node" title="站點 J" id="Point02" target="$fwd" tilt="0.25" distance="11.7678" description="" url="{node19}" pan="-265.82"/>
      <hotspot skinid="ht_node" title="站點 R 貓丁目冰淇淋" id="Point03" target="$fwd" tilt="0" distance="8.51196" description="" url="{node2}" pan="-32.4266"/>
    </hotspots>
    <media/>
    <transition softedge="0" enabled="1" zoomafteroutfov="40" zoomspeed="2" delay="none" zoomoutpause="1" blendcolor="0x000000" blendtime="1" zoomafterinfov="140" zoomin="0" zoomout="0" type="crossdissolve" zoomfov="40"/>
    <animation clipsrandom="0" useinautorotation="0" syncanimationwithvideo="0" animsequence="Animation01"/>
    <control invertwheel="0" contextvr="1" speedwheel="1" dblclickfullscreen="0" contextprojections="0" lockedwheel="0" rubberband="0" zoomcentercursor="1" contextfullscreen="1" sensitivity="8" simulatemass="1" invertcontrol="1" lockedmouse="0" hideabout="0" lockedkeyboard="0" lockedkeyboardzoom="0"/>
  </panorama>
  <panorama id="node19">
    <input levelbias="0.400" levelbiashidpi="1.000" levelingroll="0" height="3661" leveltileurl="tiles/node19/cf_%c/l_%l/c_%x/tile_%y.jpg" leveltilesize="510" width="3661" levelingpitch="0" overlap="1">
      <level height="3661" preload="0" width="3661" predecode="0"/>
      <level height="1830" preload="0" width="1830" predecode="0"/>
      <level height="915" preload="0" width="915" predecode="0"/>
      <level height="457" preload="1" width="457" predecode="1"/>
      <preview color="0x808080" strip="1"/>
    </input>
    <view pannorth="192.456" fovmode="2">
      <start tilt="0" projection="4" pan="90" fov="100"/>
      <flyin tilt="-90" projection="9" pan="0" fov="170"/>
      <min fovpixel="2" tilt="-90" pan="0"/>
      <max fovstereographic="330" tilt="90" fovfisheye="360" scaletofit="1" pan="360" fov="90"/>
    </view>
    <userdata longitude="121.61298497" heading="192.456" tags="PTGuioutput" title="站點 J" info="" author="James Lee" latitude="23.98032322" comment="" description="" nodeid="node19" copyright="jp-image.space" datetime="2024/10/14 10:18" customnodeid="" source="">
      <mapcoords y_floorplan_percent="58.214" x="0.823975" x_floorplan_percent="45.5754" y="-0.948944" mapid="FloorPlan01"/>
    </userdata>
    <hotspots height="20" smoothmovement="0" width="180" wordwrap="1">
      <label enabled="1" textcolor="0x000000" borderradius="1" wordwrap="1" bordercolor="0x000000" height="20" backgroundcolor="0xffffff" backgroundalpha="1" border="1" borderalpha="1" textalpha="1" width="180" background="1"/>
      <polystyle backgroundalpha="0.25098" backgroundcolor="0x0000ff" borderalpha="1" handcursor="1" bordercolor="0x0000ff" mode="0"/>
      <hotspot skinid="ht_node" title="站點 K 花凜和服屋 ｜探索の味" id="Point01" target="$fwd" tilt="0.49" distance="11.3579" description="" url="{node20}" pan="-275.2"/>
      <hotspot skinid="ht_node" title="站點 I 貓丁目冰淇淋" id="Point02" target="$fwd" tilt="0.21" distance="11.7678" description="" url="{node18}" pan="-95.1"/>
      <hotspot skinid="ht_node" title="站點 Ｐ" id="Point03" target="$fwd" tilt="0" distance="25.1796" description="" url="{node25}" pan="355.079"/>
    </hotspots>
    <media/>
    <transition softedge="0" enabled="1" zoomafteroutfov="40" zoomspeed="2" delay="none" zoomoutpause="1" blendcolor="0x000000" blendtime="1" zoomafterinfov="140" zoomin="0" zoomout="0" type="crossdissolve" zoomfov="40"/>
    <animation clipsrandom="0" useinautorotation="0" syncanimationwithvideo="0" animsequence="Animation01"/>
    <control invertwheel="0" contextvr="1" speedwheel="1" dblclickfullscreen="0" contextprojections="0" lockedwheel="0" rubberband="0" zoomcentercursor="1" contextfullscreen="1" sensitivity="8" simulatemass="1" invertcontrol="1" lockedmouse="0" hideabout="0" lockedkeyboard="0" lockedkeyboardzoom="0"/>
  </panorama>
  <panorama id="node20">
    <input levelbias="0.400" levelbiashidpi="1.000" levelingroll="0" height="3661" leveltileurl="tiles/node20/cf_%c/l_%l/c_%x/tile_%y.jpg" leveltilesize="510" width="3661" levelingpitch="0" overlap="1">
      <level height="3661" preload="0" width="3661" predecode="0"/>
      <level height="1830" preload="0" width="1830" predecode="0"/>
      <level height="915" preload="0" width="915" predecode="0"/>
      <level height="457" preload="1" width="457" predecode="1"/>
      <preview color="0x808080" strip="1"/>
    </input>
    <view pannorth="-185.565" fovmode="2">
      <start tilt="0" projection="4" pan="90" fov="100"/>
      <flyin tilt="-90" projection="9" pan="0" fov="170"/>
      <min fovpixel="2" tilt="-90" pan="0"/>
      <max fovstereographic="330" tilt="90" fovfisheye="360" scaletofit="1" pan="360" fov="90"/>
    </view>
    <userdata longitude="121.61309129" heading="-185.565" tags="PTGuioutput" title="站點 K 花凜和服屋 ｜探索の味" info="" author="James Lee" latitude="23.98029165" comment="" description="" nodeid="node20" copyright="jp-image.space" datetime="2024/10/14 10:12" customnodeid="" source="">
      <mapcoords y_floorplan_percent="58.214" x="0.937958" x_floorplan_percent="51.88" y="-0.948944" mapid="FloorPlan01"/>
    </userdata>
    <hotspots height="20" smoothmovement="0" width="180" wordwrap="1">
      <label enabled="1" textcolor="0x000000" borderradius="1" wordwrap="1" bordercolor="0x000000" height="20" backgroundcolor="0xffffff" backgroundalpha="1" border="1" borderalpha="1" textalpha="1" width="180" background="1"/>
      <polystyle backgroundalpha="0.25098" backgroundcolor="0x0000ff" borderalpha="1" handcursor="1" bordercolor="0x0000ff" mode="0"/>
      <hotspot skinid="ht_node" title="站點 L" id="Point01" target="$fwd" tilt="0.43" distance="11.7712" description="" url="{node21}" pan="-293.28"/>
      <hotspot skinid="ht_node" title="站點 J" id="Point02" target="$fwd" tilt="-0.08" distance="11.3579" description="" url="{node19}" pan="-111.64"/>
    </hotspots>
    <media/>
    <transition softedge="0" enabled="1" zoomafteroutfov="40" zoomspeed="2" delay="none" zoomoutpause="1" blendcolor="0x000000" blendtime="1" zoomafterinfov="140" zoomin="0" zoomout="0" type="crossdissolve" zoomfov="40"/>
    <animation clipsrandom="0" useinautorotation="0" syncanimationwithvideo="0" animsequence="Animation01"/>
    <control invertwheel="0" contextvr="1" speedwheel="1" dblclickfullscreen="0" contextprojections="0" lockedwheel="0" rubberband="0" zoomcentercursor="1" contextfullscreen="1" sensitivity="8" simulatemass="1" invertcontrol="1" lockedmouse="0" hideabout="0" lockedkeyboard="0" lockedkeyboardzoom="0"/>
  </panorama>
  <panorama id="node21">
    <input levelbias="0.400" levelbiashidpi="1.000" levelingroll="0" height="3663" leveltileurl="tiles/node21/cf_%c/l_%l/c_%x/tile_%y.jpg" leveltilesize="510" width="3663" levelingpitch="0" overlap="1">
      <level height="3663" preload="0" width="3663" predecode="0"/>
      <level height="1831" preload="0" width="1831" predecode="0"/>
      <level height="915" preload="0" width="915" predecode="0"/>
      <level height="457" preload="1" width="457" predecode="1"/>
      <preview color="0x808080" strip="1"/>
    </input>
    <view pannorth="4.36978" fovmode="2">
      <start tilt="0" projection="4" pan="90" fov="100"/>
      <flyin tilt="-90" projection="9" pan="0" fov="170"/>
      <min fovpixel="1" tilt="-90" pan="0"/>
      <max fovstereographic="330" tilt="90" fovfisheye="360" scaletofit="1" pan="360" fov="90"/>
    </view>
    <userdata longitude="121.61320062" heading="4.36978" tags="PTGuioutput" title="站點 L" info="" author="James Lee" latitude="23.98025661" comment="" description="" nodeid="node21" copyright="jp-image.space" datetime="2024/10/14 10:04" customnodeid="" source="">
      <mapcoords y_floorplan_percent="58.3825" x="1.05606" x_floorplan_percent="58.4125" y="-0.951691" mapid="FloorPlan01"/>
    </userdata>
    <hotspots height="20" smoothmovement="0" width="180" wordwrap="1">
      <label enabled="1" textcolor="0x000000" borderradius="1" wordwrap="1" bordercolor="0x000000" height="20" backgroundcolor="0xffffff" backgroundalpha="1" border="1" borderalpha="1" textalpha="1" width="180" background="1"/>
      <polystyle backgroundalpha="0.25098" backgroundcolor="0x0000ff" borderalpha="1" handcursor="1" bordercolor="0x0000ff" mode="0"/>
      <hotspot skinid="ht_node" title="站點 M 山海百貨" id="Point01" target="$fwd" tilt="0.43" distance="12.7274" description="" url="{node22}" pan="-103.41"/>
      <hotspot skinid="ht_node" title="站點 K 花凜和服屋 ｜探索の味" id="Point02" target="$fwd" tilt="0.51" distance="11.7712" description="" url="{node20}" pan="-283.36"/>
      <hotspot skinid="ht_node" title="站點Ｎ" id="Point03" target="$fwd" tilt="0.06" distance="24.771" description="" url="{node23}" pan="-193.32"/>
      <hotspot skinid="ht_node" title="站點 D 牆面介紹" id="Point04" target="$fwd" tilt="0.79" distance="35.391" description="" url="{node13}" pan="-6.22"/>
    </hotspots>
    <media/>
    <transition softedge="0" enabled="1" zoomafteroutfov="40" zoomspeed="2" delay="none" zoomoutpause="1" blendcolor="0x000000" blendtime="1" zoomafterinfov="140" zoomin="0" zoomout="0" type="crossdissolve" zoomfov="40"/>
    <animation clipsrandom="0" useinautorotation="0" syncanimationwithvideo="0" animsequence="Animation01"/>
    <control invertwheel="0" contextvr="1" speedwheel="1" dblclickfullscreen="0" contextprojections="0" lockedwheel="0" rubberband="0" zoomcentercursor="1" contextfullscreen="1" sensitivity="8" simulatemass="1" invertcontrol="1" lockedmouse="0" hideabout="0" lockedkeyboard="0" lockedkeyboardzoom="0"/>
  </panorama>
  <panorama id="node22">
    <input levelbias="0.400" levelbiashidpi="1.000" levelingroll="0" height="3662" leveltileurl="tiles/node22/cf_%c/l_%l/c_%x/tile_%y.jpg" leveltilesize="510" width="3662" levelingpitch="0" overlap="1">
      <level height="3662" preload="0" width="3662" predecode="0"/>
      <level height="1831" preload="0" width="1831" predecode="0"/>
      <level height="915" preload="0" width="915" predecode="0"/>
      <level height="457" preload="1" width="457" predecode="1"/>
      <preview color="0x808080" strip="1"/>
    </input>
    <view pannorth="230.369" fovmode="2">
      <start tilt="0" projection="4" pan="90" fov="100"/>
      <flyin tilt="-90" projection="9" pan="0" fov="170"/>
      <min fovpixel="2" tilt="-90" pan="0"/>
      <max fovstereographic="330" tilt="90" fovfisheye="360" scaletofit="1" pan="360" fov="90"/>
    </view>
    <userdata longitude="121.61332017" heading="230.369" tags="PTGuioutput" title="站點 M 山海百貨" info="" author="James Lee" latitude="23.98022241" comment="" description="" nodeid="node22" copyright="jp-image.space" datetime="2024/10/14 10:04" customnodeid="" source="">
      <mapcoords y_floorplan_percent="58.2982" x="1.18378" x_floorplan_percent="65.4766" y="-0.950317" mapid="FloorPlan01"/>
    </userdata>
    <hotspots height="20" smoothmovement="0" width="180" wordwrap="1">
      <label enabled="1" textcolor="0x000000" borderradius="1" wordwrap="1" bordercolor="0x000000" height="20" backgroundcolor="0xffffff" backgroundalpha="1" border="1" borderalpha="1" textalpha="1" width="180" background="1"/>
      <polystyle backgroundalpha="0.25098" backgroundcolor="0x0000ff" borderalpha="1" handcursor="1" bordercolor="0x0000ff" mode="0"/>
      <hotspot skinid="ht_node" title="站點 L" id="Point01" target="$fwd" tilt="0.58" distance="12.7274" description="" url="{node21}" pan="-56.89"/>
      <hotspot skinid="ht_node" title="站點 S 山海百貨" id="Point02" target="$fwd" tilt="-0.73" distance="10.5892" description="" url="{node3}" pan="-3.96"/>
    </hotspots>
    <media/>
    <transition softedge="0" enabled="1" zoomafteroutfov="40" zoomspeed="2" delay="none" zoomoutpause="1" blendcolor="0x000000" blendtime="1" zoomafterinfov="140" zoomin="0" zoomout="0" type="crossdissolve" zoomfov="40"/>
    <animation clipsrandom="0" useinautorotation="0" syncanimationwithvideo="0" animsequence="Animation01"/>
    <control invertwheel="0" contextvr="1" speedwheel="1" dblclickfullscreen="0" contextprojections="0" lockedwheel="0" rubberband="0" zoomcentercursor="1" contextfullscreen="1" sensitivity="8" simulatemass="1" invertcontrol="1" lockedmouse="0" hideabout="0" lockedkeyboard="0" lockedkeyboardzoom="0"/>
  </panorama>
  <panorama id="node23">
    <input levelbias="0.400" levelbiashidpi="1.000" levelingroll="0" height="3660" leveltileurl="tiles/node23/cf_%c/l_%l/c_%x/tile_%y.jpg" leveltilesize="510" width="3660" levelingpitch="0" overlap="1">
      <level height="3660" preload="0" width="3660" predecode="0"/>
      <level height="1830" preload="0" width="1830" predecode="0"/>
      <level height="915" preload="0" width="915" predecode="0"/>
      <level height="457" preload="1" width="457" predecode="1"/>
      <preview color="0x808080" strip="1"/>
    </input>
    <view pannorth="143.865" fovmode="2">
      <start tilt="0" projection="4" pan="90" fov="100"/>
      <flyin tilt="-90" projection="9" pan="0" fov="170"/>
      <min fovpixel="2" tilt="-90" pan="0"/>
      <max fovstereographic="330" tilt="90" fovfisheye="360" scaletofit="1" pan="360" fov="90"/>
    </view>
    <userdata longitude="121.61312145" heading="143.865" tags="PTGuioutput" title="站點Ｎ" info="" author="James Lee" latitude="23.98004591" comment="" description="" nodeid="node23" copyright="jp-image.space" datetime="2024/10/14 11:06" customnodeid="" source="">
      <mapcoords y_floorplan_percent="73.631" x="1.05194" x_floorplan_percent="58.1846" y="-1.20026" mapid="FloorPlan01"/>
    </userdata>
    <hotspots height="20" smoothmovement="0" width="180" wordwrap="1">
      <label enabled="1" textcolor="0x000000" borderradius="1" wordwrap="1" bordercolor="0x000000" height="20" backgroundcolor="0xffffff" backgroundalpha="1" border="1" borderalpha="1" textalpha="1" width="180" background="1"/>
      <polystyle backgroundalpha="0.25098" backgroundcolor="0x0000ff" borderalpha="1" handcursor="1" bordercolor="0x0000ff" mode="0"/>
      <hotspot skinid="ht_node" title="站點 L" id="Point01" target="$fwd" tilt="0.26" distance="24.771" description="" url="{node21}" pan="-233.65"/>
      <hotspot skinid="ht_node" title="站點 X 小藍肥皂" id="Point02" target="$fwd" tilt="-0.78" distance="7.88017" description="" url="{node8}" pan="-34.25"/>
      <hotspot skinid="ht_node" title="站點 Ｐ" id="Point03" target="$fwd" tilt="0" distance="22.4428" description="" url="{node25}" pan="216.214"/>
    </hotspots>
    <media/>
    <transition softedge="0" enabled="1" zoomafteroutfov="40" zoomspeed="2" delay="none" zoomoutpause="1" blendcolor="0x000000" blendtime="1" zoomafterinfov="140" zoomin="0" zoomout="0" type="crossdissolve" zoomfov="40"/>
    <animation clipsrandom="0" useinautorotation="0" syncanimationwithvideo="0" animsequence="Animation01"/>
    <control invertwheel="0" contextvr="1" speedwheel="1" dblclickfullscreen="0" contextprojections="0" lockedwheel="0" rubberband="0" zoomcentercursor="1" contextfullscreen="1" sensitivity="8" simulatemass="1" invertcontrol="1" lockedmouse="0" hideabout="0" lockedkeyboard="0" lockedkeyboardzoom="0"/>
  </panorama>
  <panorama id="node24">
    <input levelbias="0.400" levelbiashidpi="1.000" levelingroll="0" height="3660" leveltileurl="tiles/node24/cf_%c/l_%l/c_%x/tile_%y.jpg" leveltilesize="510" width="3660" levelingpitch="0" overlap="1">
      <level height="3660" preload="0" width="3660" predecode="0"/>
      <level height="1830" preload="0" width="1830" predecode="0"/>
      <level height="915" preload="0" width="915" predecode="0"/>
      <level height="457" preload="1" width="457" predecode="1"/>
      <preview color="0x808080" strip="1"/>
    </input>
    <view pannorth="-79.754" fovmode="2">
      <start tilt="0" projection="4" pan="90" fov="100"/>
      <flyin tilt="-90" projection="9" pan="0" fov="170"/>
      <min fovpixel="2" tilt="-90" pan="0"/>
      <max fovstereographic="330" tilt="90" fovfisheye="360" scaletofit="1" pan="360" fov="90"/>
    </view>
    <userdata longitude="121.61269018" heading="-79.754" tags="PTGuioutput" title="站點 Ｏ" info="" author="James Lee" latitude="23.98017523" comment="" description="" nodeid="node24" copyright="jp-image.space" datetime="2024/10/14 11:01" customnodeid="" source="">
      <mapcoords y_floorplan_percent="73.5468" x="0.589142" x_floorplan_percent="32.5864" y="-1.19888" mapid="FloorPlan01"/>
    </userdata>
    <hotspots height="20" smoothmovement="0" width="180" wordwrap="1">
      <label enabled="1" textcolor="0x000000" borderradius="1" wordwrap="1" bordercolor="0x000000" height="20" backgroundcolor="0xffffff" backgroundalpha="1" border="1" borderalpha="1" textalpha="1" width="180" background="1"/>
      <polystyle backgroundalpha="0.25098" backgroundcolor="0x0000ff" borderalpha="1" handcursor="1" bordercolor="0x0000ff" mode="0"/>
      <hotspot skinid="ht_node" title="站點 H 炸彈檸檬茶" id="Point01" target="$fwd" tilt="0.52" distance="24.6325" description="" url="{node17}" pan="-96.95"/>
      <hotspot skinid="ht_node" title="站點 Ｐ" id="Point02" target="$fwd" tilt="-0.59" distance="23.6741" description="" url="{node25}" pan="-188.11"/>
    </hotspots>
    <media/>
    <transition softedge="0" enabled="1" zoomafteroutfov="40" zoomspeed="2" delay="none" zoomoutpause="1" blendcolor="0x000000" blendtime="1" zoomafterinfov="140" zoomin="0" zoomout="0" type="crossdissolve" zoomfov="40"/>
    <animation clipsrandom="0" useinautorotation="0" syncanimationwithvideo="0" animsequence="Animation01"/>
    <control invertwheel="0" contextvr="1" speedwheel="1" dblclickfullscreen="0" contextprojections="0" lockedwheel="0" rubberband="0" zoomcentercursor="1" contextfullscreen="1" sensitivity="8" simulatemass="1" invertcontrol="1" lockedmouse="0" hideabout="0" lockedkeyboard="0" lockedkeyboardzoom="0"/>
  </panorama>
  <panorama id="node25">
    <input levelbias="0.400" levelbiashidpi="1.000" levelingroll="0" height="3659" leveltileurl="tiles/node25/cf_%c/l_%l/c_%x/tile_%y.jpg" leveltilesize="510" width="3659" levelingpitch="0" overlap="1">
      <level height="3659" preload="0" width="3659" predecode="0"/>
      <level height="1829" preload="0" width="1829" predecode="0"/>
      <level height="914" preload="0" width="914" predecode="0"/>
      <level height="457" preload="1" width="457" predecode="1"/>
      <preview color="0x808080" strip="1"/>
    </input>
    <view pannorth="151.619" fovmode="2">
      <start tilt="0" projection="4" pan="90" fov="100"/>
      <flyin tilt="-90" projection="9" pan="0" fov="170"/>
      <min fovpixel="2" tilt="-90" pan="0"/>
      <max fovstereographic="330" tilt="90" fovfisheye="360" scaletofit="1" pan="360" fov="90"/>
    </view>
    <userdata longitude="121.61291095" heading="151.619" tags="PTGuioutput" title="站點 Ｐ" info="" author="James Lee" latitude="23.98010711" comment="" description="" nodeid="node25" copyright="jp-image.space" datetime="2024/10/16 9:58" customnodeid="" source="">
      <mapcoords y_floorplan_percent="73.6731" x="0.826035" x_floorplan_percent="45.6893" y="-1.20094" mapid="FloorPlan01"/>
    </userdata>
    <hotspots height="20" smoothmovement="0" width="180" wordwrap="1">
      <label enabled="1" textcolor="0x000000" borderradius="1" wordwrap="1" bordercolor="0x000000" height="20" backgroundcolor="0xffffff" backgroundalpha="1" border="1" borderalpha="1" textalpha="1" width="180" background="1"/>
      <polystyle backgroundalpha="0.25098" backgroundcolor="0x0000ff" borderalpha="1" handcursor="1" bordercolor="0x0000ff" mode="0"/>
      <hotspot skinid="ht_node" title="站點 J" id="Point01" target="$fwd" tilt="-1.29" distance="25.1796" description="" url="{node19}" pan="-226.82"/>
      <hotspot skinid="ht_node" title="站點Ｎ" id="Point02" target="$fwd" tilt="0.46" distance="22.4428" description="" url="{node23}" pan="-316.56"/>
      <hotspot skinid="ht_node" title="站點 Ｏ" id="Point03" target="$fwd" tilt="0" distance="23.6741" description="" url="{node24}" pan="222.959"/>
    </hotspots>
    <media/>
    <transition softedge="0" enabled="1" zoomafteroutfov="40" zoomspeed="2" delay="none" zoomoutpause="1" blendcolor="0x000000" blendtime="1" zoomafterinfov="140" zoomin="0" zoomout="0" type="crossdissolve" zoomfov="40"/>
    <animation clipsrandom="0" useinautorotation="0" syncanimationwithvideo="0" animsequence="Animation01"/>
    <control invertwheel="0" contextvr="1" speedwheel="1" dblclickfullscreen="0" contextprojections="0" lockedwheel="0" rubberband="0" zoomcentercursor="1" contextfullscreen="1" sensitivity="8" simulatemass="1" invertcontrol="1" lockedmouse="0" hideabout="0" lockedkeyboard="0" lockedkeyboardzoom="0"/>
  </panorama>
  <panorama id="node1">
    <input levelbias="0.400" levelbiashidpi="1.000" levelingroll="0" height="3651" leveltileurl="tiles/node1/cf_%c/l_%l/c_%x/tile_%y.jpg" leveltilesize="510" width="3651" levelingpitch="0" overlap="1">
      <level height="3651" preload="0" width="3651" predecode="0"/>
      <level height="1825" preload="0" width="1825" predecode="0"/>
      <level height="912" preload="0" width="912" predecode="0"/>
      <level height="456" preload="1" width="456" predecode="1"/>
      <preview color="0x808080" strip="1"/>
    </input>
    <view pannorth="-49.6519" fovmode="2">
      <start tilt="0" projection="4" pan="90" fov="100"/>
      <flyin tilt="-90" projection="9" pan="0" fov="170"/>
      <min fovpixel="2" tilt="-90" pan="0"/>
      <max fovstereographic="330" tilt="90" fovfisheye="360" scaletofit="1" pan="360" fov="90"/>
    </view>
    <userdata longitude="121.61262470" heading="-49.6519" tags="PTGuioutput" title="站點Ｑ 防空洞" info="" author="James Lee" latitude="23.98046899" comment="" description="" nodeid="node1" copyright="jp-image.space" datetime="2024/10/14 11:30" customnodeid="" source="">
      <mapcoords y_floorplan_percent="55.6866" x="0.424347" x_floorplan_percent="23.4713" y="-0.907745" mapid="FloorPlan01"/>
    </userdata>
    <hotspots height="20" smoothmovement="0" width="180" wordwrap="1">
      <label enabled="1" textcolor="0x000000" borderradius="1" wordwrap="1" bordercolor="0x000000" height="20" backgroundcolor="0xffffff" backgroundalpha="1" border="1" borderalpha="1" textalpha="1" width="180" background="1"/>
      <polystyle backgroundalpha="0.25098" backgroundcolor="0x0000ff" borderalpha="1" handcursor="1" bordercolor="0x0000ff" mode="0"/>
      <hotspot skinid="ht_node" title="站點 G 家咖哩" id="Point01" target="$fwd" tilt="0" distance="7.14238" description="" url="{node16}" pan="-194.086"/>
    </hotspots>
    <media/>
    <transition softedge="0" enabled="1" zoomafteroutfov="40" zoomspeed="2" delay="none" zoomoutpause="1" blendcolor="0x000000" blendtime="1" zoomafterinfov="140" zoomin="0" zoomout="0" type="crossdissolve" zoomfov="40"/>
    <animation clipsrandom="0" useinautorotation="0" syncanimationwithvideo="0" animsequence="Animation01"/>
    <control invertwheel="0" contextvr="1" speedwheel="1" dblclickfullscreen="0" contextprojections="0" lockedwheel="0" rubberband="0" zoomcentercursor="1" contextfullscreen="1" sensitivity="8" simulatemass="1" invertcontrol="1" lockedmouse="0" hideabout="0" lockedkeyboard="0" lockedkeyboardzoom="0"/>
  </panorama>
  <panorama id="node2">
    <input levelbias="0.400" levelbiashidpi="1.000" levelingroll="0" height="3655" leveltileurl="tiles/node2/cf_%c/l_%l/c_%x/tile_%y.jpg" leveltilesize="510" width="3655" levelingpitch="0" overlap="1">
      <level height="3655" preload="0" width="3655" predecode="0"/>
      <level height="1827" preload="0" width="1827" predecode="0"/>
      <level height="913" preload="0" width="913" predecode="0"/>
      <level height="456" preload="1" width="456" predecode="1"/>
      <preview color="0x808080" strip="1"/>
    </input>
    <view pannorth="105.658" fovmode="2">
      <start tilt="0" projection="4" pan="90" fov="100"/>
      <flyin tilt="-90" projection="9" pan="0" fov="170"/>
      <min fovpixel="2" tilt="-90" pan="0"/>
      <max fovstereographic="330" tilt="90" fovfisheye="360" scaletofit="1" pan="360" fov="90"/>
    </view>
    <userdata longitude="121.61280660" heading="105.658" tags="PTGuioutput" title="站點 R 貓丁目冰淇淋" info="" author="James Lee" latitude="23.98031147" comment="" description="" nodeid="node2" copyright="jp-image.space" datetime="2024/10/14 11:39" customnodeid="" source="">
      <mapcoords y_floorplan_percent="62.4263" x="0.65506" x_floorplan_percent="36.2324" y="-1.01761" mapid="FloorPlan01"/>
    </userdata>
    <hotspots height="20" smoothmovement="0" width="180" wordwrap="1">
      <label enabled="1" textcolor="0x000000" borderradius="1" wordwrap="1" bordercolor="0x000000" height="20" backgroundcolor="0xffffff" backgroundalpha="1" border="1" borderalpha="1" textalpha="1" width="180" background="1"/>
      <polystyle backgroundalpha="0.25098" backgroundcolor="0x0000ff" borderalpha="1" handcursor="1" bordercolor="0x0000ff" mode="0"/>
      <hotspot skinid="ht_node" title="站點 H 炸彈檸檬茶" id="Point02" target="$fwd" tilt="-1.53" distance="9.3865" description="" url="{node17}" pan="-227.06"/>
      <hotspot skinid="ht_node" title="站點 I 貓丁目冰淇淋" id="Point01" target="$fwd" tilt="0" distance="8.51196" description="" url="{node18}" pan="51.1555"/>
    </hotspots>
    <media/>
    <transition softedge="0" enabled="1" zoomafteroutfov="40" zoomspeed="2" delay="none" zoomoutpause="1" blendcolor="0x000000" blendtime="1" zoomafterinfov="140" zoomin="0" zoomout="0" type="crossdissolve" zoomfov="40"/>
    <animation clipsrandom="0" useinautorotation="0" syncanimationwithvideo="0" animsequence="Animation01"/>
    <control invertwheel="0" contextvr="1" speedwheel="1" dblclickfullscreen="0" contextprojections="0" lockedwheel="0" rubberband="0" zoomcentercursor="1" contextfullscreen="1" sensitivity="8" simulatemass="1" invertcontrol="1" lockedmouse="0" hideabout="0" lockedkeyboard="0" lockedkeyboardzoom="0"/>
  </panorama>
  <panorama id="node3">
    <input levelbias="0.400" levelbiashidpi="1.000" levelingroll="0" height="3649" leveltileurl="tiles/node3/cf_%c/l_%l/c_%x/tile_%y.jpg" leveltilesize="510" width="3649" levelingpitch="0" overlap="1">
      <level height="3649" preload="0" width="3649" predecode="0"/>
      <level height="1824" preload="0" width="1824" predecode="0"/>
      <level height="912" preload="0" width="912" predecode="0"/>
      <level height="456" preload="1" width="456" predecode="1"/>
      <preview color="0x808080" strip="1"/>
    </input>
    <view pannorth="-90.5389" fovmode="2">
      <start tilt="0" projection="4" pan="90" fov="100"/>
      <flyin tilt="-90" projection="9" pan="0" fov="170"/>
      <min fovpixel="2" tilt="-90" pan="0"/>
      <max fovstereographic="330" tilt="90" fovfisheye="360" scaletofit="1" pan="360" fov="90"/>
    </view>
    <userdata longitude="121.61323932" heading="-90.5389" tags="PTGuioutput" title="站點 S 山海百貨" info="" author="James Lee" latitude="23.98016231" comment="" description="" nodeid="node3" copyright="jp-image.space" datetime="2024/10/14 12:10" customnodeid="" source="">
      <mapcoords y_floorplan_percent="63.7321" x="1.1261" x_floorplan_percent="62.2864" y="-1.03889" mapid="FloorPlan01"/>
    </userdata>
    <hotspots height="20" smoothmovement="0" width="180" wordwrap="1">
      <label enabled="1" textcolor="0x000000" borderradius="1" wordwrap="1" bordercolor="0x000000" height="20" backgroundcolor="0xffffff" backgroundalpha="1" border="1" borderalpha="1" textalpha="1" width="180" background="1"/>
      <polystyle backgroundalpha="0.25098" backgroundcolor="0x0000ff" borderalpha="1" handcursor="1" bordercolor="0x0000ff" mode="0"/>
      <hotspot skinid="ht_node" title="站點 L" id="Point01" target="$fwd" tilt="-3.36" distance="11.1986" description="" url="{node21}" pan="-76.16"/>
      <hotspot tilt="-0.67" skinid="ht_node" title="站點 T 山海百貨" description="" id="Point02" url="{node6}" pan="-281.89" target="$fwd"/>
    </hotspots>
    <media/>
    <transition softedge="0" enabled="1" zoomafteroutfov="40" zoomspeed="2" delay="none" zoomoutpause="1" blendcolor="0x000000" blendtime="1" zoomafterinfov="140" zoomin="0" zoomout="0" type="crossdissolve" zoomfov="40"/>
    <animation clipsrandom="0" useinautorotation="0" syncanimationwithvideo="0" animsequence="Animation01"/>
    <control invertwheel="0" contextvr="1" speedwheel="1" dblclickfullscreen="0" contextprojections="0" lockedwheel="0" rubberband="0" zoomcentercursor="1" contextfullscreen="1" sensitivity="8" simulatemass="1" invertcontrol="1" lockedmouse="0" hideabout="0" lockedkeyboard="0" lockedkeyboardzoom="0"/>
  </panorama>
  <panorama id="node6">
    <input levelbias="0.400" levelbiashidpi="1.000" levelingroll="0" height="3654" leveltileurl="tiles/node6/cf_%c/l_%l/c_%x/tile_%y.jpg" leveltilesize="510" width="3654" levelingpitch="0" overlap="1">
      <level height="3654" preload="0" width="3654" predecode="0"/>
      <level height="1827" preload="0" width="1827" predecode="0"/>
      <level height="913" preload="0" width="913" predecode="0"/>
      <level height="456" preload="1" width="456" predecode="1"/>
      <preview color="0x808080" strip="1"/>
    </input>
    <view pannorth="-96.1651" fovmode="2">
      <start tilt="0" projection="4" pan="90" fov="100"/>
      <flyin tilt="-90" projection="9" pan="0" fov="170"/>
      <min fovpixel="2" tilt="-90" pan="0"/>
      <max fovstereographic="330" tilt="90" fovfisheye="360" scaletofit="1" pan="360" fov="90"/>
    </view>
    <userdata longitude="" heading="-96.1651" tags="PTGuioutput" title="站點 T 山海百貨" info="" author="James Lee" latitude="" comment="" description="" nodeid="node6" copyright="jp-image.space" datetime="2024/10/14 12:24" customnodeid="" source=""/>
    <hotspots height="20" smoothmovement="0" width="180" wordwrap="1">
      <label enabled="1" textcolor="0x000000" borderradius="1" wordwrap="1" bordercolor="0x000000" height="20" backgroundcolor="0xffffff" backgroundalpha="1" border="1" borderalpha="1" textalpha="1" width="180" background="1"/>
      <polystyle backgroundalpha="0.25098" backgroundcolor="0x0000ff" borderalpha="1" handcursor="1" bordercolor="0x0000ff" mode="0"/>
      <hotspot tilt="2.69" skinid="ht_node" title="站點 S 山海百貨" description="" id="Point01" url="{node3}" pan="-115.23" target="$fwd"/>
      <hotspot tilt="1.23" skinid="ht_node" title="站點 Ｕ山海百貨" description="" id="Point02" url="{node4}" pan="-310.85" target="$fwd"/>
      <hotspot tilt="-1.76" skinid="ht_node" title="站點 V 山海百貨" description="" id="Point03" url="{node5}" pan="-243.08" target="$fwd"/>
    </hotspots>
    <media/>
    <transition softedge="0" enabled="1" zoomafteroutfov="40" zoomspeed="2" delay="none" zoomoutpause="1" blendcolor="0x000000" blendtime="1" zoomafterinfov="140" zoomin="0" zoomout="0" type="crossdissolve" zoomfov="40"/>
    <animation clipsrandom="0" useinautorotation="0" syncanimationwithvideo="0" animsequence="Animation01"/>
    <control invertwheel="0" contextvr="1" speedwheel="1" dblclickfullscreen="0" contextprojections="0" lockedwheel="0" rubberband="0" zoomcentercursor="1" contextfullscreen="1" sensitivity="8" simulatemass="1" invertcontrol="1" lockedmouse="0" hideabout="0" lockedkeyboard="0" lockedkeyboardzoom="0"/>
  </panorama>
  <panorama id="node4">
    <input levelbias="0.400" levelbiashidpi="1.000" levelingroll="0" height="3654" leveltileurl="tiles/node4/cf_%c/l_%l/c_%x/tile_%y.jpg" leveltilesize="510" width="3654" levelingpitch="0" overlap="1">
      <level height="3654" preload="0" width="3654" predecode="0"/>
      <level height="1827" preload="0" width="1827" predecode="0"/>
      <level height="913" preload="0" width="913" predecode="0"/>
      <level height="456" preload="1" width="456" predecode="1"/>
      <preview color="0x808080" strip="1"/>
    </input>
    <view pannorth="0" fovmode="2">
      <start tilt="0" projection="4" pan="90" fov="100"/>
      <flyin tilt="-90" projection="9" pan="0" fov="170"/>
      <min fovpixel="2" tilt="-90" pan="0"/>
      <max fovstereographic="330" tilt="90" fovfisheye="360" scaletofit="1" pan="360" fov="90"/>
    </view>
    <userdata longitude="" heading="0" tags="PTGuioutput" title="站點 Ｕ山海百貨" info="" author="James Lee" latitude="" comment="" description="" nodeid="node4" copyright="jp-image.space" datetime="2024/10/14 12:15" customnodeid="" source=""/>
    <hotspots height="20" smoothmovement="0" width="180" wordwrap="1">
      <label enabled="1" textcolor="0x000000" borderradius="1" wordwrap="1" bordercolor="0x000000" height="20" backgroundcolor="0xffffff" backgroundalpha="1" border="1" borderalpha="1" textalpha="1" width="180" background="1"/>
      <polystyle backgroundalpha="0.25098" backgroundcolor="0x0000ff" borderalpha="1" handcursor="1" bordercolor="0x0000ff" mode="0"/>
      <hotspot tilt="0.47" skinid="ht_node" title="站點 T 山海百貨" description="" id="Point01" url="{node6}" pan="-337.73" target="$fwd"/>
    </hotspots>
    <media/>
    <transition softedge="0" enabled="1" zoomafteroutfov="40" zoomspeed="2" delay="none" zoomoutpause="1" blendcolor="0x000000" blendtime="1" zoomafterinfov="140" zoomin="0" zoomout="0" type="crossdissolve" zoomfov="40"/>
    <animation clipsrandom="0" useinautorotation="0" syncanimationwithvideo="0" animsequence="Animation01"/>
    <control invertwheel="0" contextvr="1" speedwheel="1" dblclickfullscreen="0" contextprojections="0" lockedwheel="0" rubberband="0" zoomcentercursor="1" contextfullscreen="1" sensitivity="8" simulatemass="1" invertcontrol="1" lockedmouse="0" hideabout="0" lockedkeyboard="0" lockedkeyboardzoom="0"/>
  </panorama>
  <panorama id="node5">
    <input levelbias="0.400" levelbiashidpi="1.000" levelingroll="0" height="3654" leveltileurl="tiles/node5/cf_%c/l_%l/c_%x/tile_%y.jpg" leveltilesize="510" width="3654" levelingpitch="0" overlap="1">
      <level height="3654" preload="0" width="3654" predecode="0"/>
      <level height="1827" preload="0" width="1827" predecode="0"/>
      <level height="913" preload="0" width="913" predecode="0"/>
      <level height="456" preload="1" width="456" predecode="1"/>
      <preview color="0x808080" strip="1"/>
    </input>
    <view pannorth="0" fovmode="2">
      <start tilt="0" projection="4" pan="90" fov="100"/>
      <flyin tilt="-90" projection="9" pan="0" fov="170"/>
      <min fovpixel="2" tilt="-90" pan="0"/>
      <max fovstereographic="330" tilt="90" fovfisheye="360" scaletofit="1" pan="360" fov="90"/>
    </view>
    <userdata longitude="" heading="0" tags="PTGuioutput" title="站點 V 山海百貨" info="" author="James Lee" latitude="" comment="" description="" nodeid="node5" copyright="jp-image.space" datetime="2024/10/14 12:19" customnodeid="" source=""/>
    <hotspots height="20" smoothmovement="0" width="180" wordwrap="1">
      <label enabled="1" textcolor="0x000000" borderradius="1" wordwrap="1" bordercolor="0x000000" height="20" backgroundcolor="0xffffff" backgroundalpha="1" border="1" borderalpha="1" textalpha="1" width="180" background="1"/>
      <polystyle backgroundalpha="0.25098" backgroundcolor="0x0000ff" borderalpha="1" handcursor="1" bordercolor="0x0000ff" mode="0"/>
      <hotspot tilt="1.01" skinid="ht_node" title="站點 T 山海百貨" description="" id="Point01" url="{node6}" pan="-303.15" target="$fwd"/>
      <hotspot tilt="0.47" skinid="ht_node" title="站點 W 山海百貨" description="" id="Point02" url="{node7}" pan="-7.66" target="$fwd"/>
    </hotspots>
    <media/>
    <transition softedge="0" enabled="1" zoomafteroutfov="40" zoomspeed="2" delay="none" zoomoutpause="1" blendcolor="0x000000" blendtime="1" zoomafterinfov="140" zoomin="0" zoomout="0" type="crossdissolve" zoomfov="40"/>
    <animation clipsrandom="0" useinautorotation="0" syncanimationwithvideo="0" animsequence="Animation01"/>
    <control invertwheel="0" contextvr="1" speedwheel="1" dblclickfullscreen="0" contextprojections="0" lockedwheel="0" rubberband="0" zoomcentercursor="1" contextfullscreen="1" sensitivity="8" simulatemass="1" invertcontrol="1" lockedmouse="0" hideabout="0" lockedkeyboard="0" lockedkeyboardzoom="0"/>
  </panorama>
  <panorama id="node7">
    <input levelbias="0.400" levelbiashidpi="1.000" levelingroll="0" height="3654" leveltileurl="tiles/node7/cf_%c/l_%l/c_%x/tile_%y.jpg" leveltilesize="510" width="3654" levelingpitch="0" overlap="1">
      <level height="3654" preload="0" width="3654" predecode="0"/>
      <level height="1827" preload="0" width="1827" predecode="0"/>
      <level height="913" preload="0" width="913" predecode="0"/>
      <level height="456" preload="1" width="456" predecode="1"/>
      <preview color="0x808080" strip="1"/>
    </input>
    <view pannorth="0" fovmode="2">
      <start tilt="0" projection="4" pan="90" fov="100"/>
      <flyin tilt="-90" projection="9" pan="0" fov="170"/>
      <min fovpixel="2" tilt="-90" pan="0"/>
      <max fovstereographic="330" tilt="90" fovfisheye="360" scaletofit="1" pan="360" fov="90"/>
    </view>
    <userdata longitude="" heading="0" tags="PTGuioutput" title="站點 W 山海百貨" info="" author="James Lee" latitude="" comment="" description="" nodeid="node7" copyright="jp-image.space" datetime="2024/10/14 12:27" customnodeid="" source=""/>
    <hotspots height="20" smoothmovement="0" width="180" wordwrap="1">
      <label enabled="1" textcolor="0x000000" borderradius="1" wordwrap="1" bordercolor="0x000000" height="20" backgroundcolor="0xffffff" backgroundalpha="1" border="1" borderalpha="1" textalpha="1" width="180" background="1"/>
      <polystyle backgroundalpha="0.25098" backgroundcolor="0x0000ff" borderalpha="1" handcursor="1" bordercolor="0x0000ff" mode="0"/>
      <hotspot tilt="2.44" skinid="ht_node" title="站點 S 山海百貨" description="" id="Point01" url="{node3}" pan="-48.16" target="$fwd"/>
      <hotspot tilt="-1.47" skinid="ht_node" title="站點 V 山海百貨" description="" id="Point02" url="{node5}" pan="-313.52" target="$fwd"/>
    </hotspots>
    <media/>
    <transition softedge="0" enabled="1" zoomafteroutfov="40" zoomspeed="2" delay="none" zoomoutpause="1" blendcolor="0x000000" blendtime="1" zoomafterinfov="140" zoomin="0" zoomout="0" type="crossdissolve" zoomfov="40"/>
    <animation clipsrandom="0" useinautorotation="0" syncanimationwithvideo="0" animsequence="Animation01"/>
    <control invertwheel="0" contextvr="1" speedwheel="1" dblclickfullscreen="0" contextprojections="0" lockedwheel="0" rubberband="0" zoomcentercursor="1" contextfullscreen="1" sensitivity="8" simulatemass="1" invertcontrol="1" lockedmouse="0" hideabout="0" lockedkeyboard="0" lockedkeyboardzoom="0"/>
  </panorama>
  <panorama id="node8">
    <input levelbias="0.400" levelbiashidpi="1.000" levelingroll="0" height="3654" leveltileurl="tiles/node8/cf_%c/l_%l/c_%x/tile_%y.jpg" leveltilesize="510" width="3654" levelingpitch="0" overlap="1">
      <level height="3654" preload="0" width="3654" predecode="0"/>
      <level height="1827" preload="0" width="1827" predecode="0"/>
      <level height="913" preload="0" width="913" predecode="0"/>
      <level height="456" preload="1" width="456" predecode="1"/>
      <preview color="0x808080" strip="1"/>
    </input>
    <view pannorth="128.342" fovmode="2">
      <start tilt="0" projection="4" pan="90" fov="100"/>
      <flyin tilt="-90" projection="9" pan="0" fov="170"/>
      <min fovpixel="2" tilt="-90" pan="0"/>
      <max fovstereographic="330" tilt="90" fovfisheye="360" scaletofit="1" pan="360" fov="90"/>
    </view>
    <userdata longitude="121.61312459" heading="128.342" tags="PTGuioutput" title="站點 X 小藍肥皂" info="" author="James Lee" latitude="23.97997510" comment="" description="" nodeid="node8" copyright="jp-image.space" datetime="2024/10/14 13:14" customnodeid="" source="">
      <mapcoords y_floorplan_percent="78.1382" x="1.07872" x_floorplan_percent="59.6658" y="-1.27373" mapid="FloorPlan01"/>
    </userdata>
    <hotspots height="20" smoothmovement="0" width="180" wordwrap="1">
      <label enabled="1" textcolor="0x000000" borderradius="1" wordwrap="1" bordercolor="0x000000" height="20" backgroundcolor="0xffffff" backgroundalpha="1" border="1" borderalpha="1" textalpha="1" width="180" background="1"/>
      <polystyle backgroundalpha="0.25098" backgroundcolor="0x0000ff" borderalpha="1" handcursor="1" bordercolor="0x0000ff" mode="0"/>
      <hotspot skinid="ht_node" title="站點Ｎ" id="Point01" target="$fwd" tilt="-2.37" distance="7.88017" description="" url="{node23}" pan="-232.74"/>
      <hotspot tilt="-15.31" skinid="ht_video_youtube" title="精緻手工皂DIY組操作說明" description="" id="Point02" url="kFHktbzuSK8&amp;si=vvfac45WUej7e1c_" pan="-122.94" target="_parent"/>
    </hotspots>
    <media/>
    <transition softedge="0" enabled="1" zoomafteroutfov="40" zoomspeed="2" delay="none" zoomoutpause="1" blendcolor="0x000000" blendtime="1" zoomafterinfov="140" zoomin="0" zoomout="0" type="crossdissolve" zoomfov="40"/>
    <animation clipsrandom="0" useinautorotation="0" syncanimationwithvideo="0" animsequence="Animation01"/>
    <control invertwheel="0" contextvr="1" speedwheel="1" dblclickfullscreen="0" contextprojections="0" lockedwheel="0" rubberband="0" zoomcentercursor="1" contextfullscreen="1" sensitivity="8" simulatemass="1" invertcontrol="1" lockedmouse="0" hideabout="0" lockedkeyboard="0" lockedkeyboardzoom="0"/>
  </panorama>
  <masternode>
    <userdata comment="" tags="" title="將軍府導覽" description="" copyright="" author=""/>
    <animationsequences>
      <sequence title="Animation01"/>
    </animationsequences>
  </masternode>
  <map mapprovider="openstreetmap" mapstyle="streets" title="" id="Map01" index="0" googlecustomstylecode="" mapurltemplate="http://{s}.tile.openstreetmap.org/{z}/{x}/{y}.png" type="web" mapmaxzoom="18"/>
  <map zoomlevels="5" tileformat="png" title="" bgcolor="rgba(255, 255, 255, 1)" crispedges="0" id="FloorPlan01" index="1" transparent="0" height="2374" floorplannorth="342" width="2633" type="file"/>
</tour>
